micropython_mc3479/__init__.py
micropython_mc3479/i2c_helpers.py
micropython_mc3479/mc3479.py
micropython_mc3479-0.4.4.dist-info/LICENSE
micropython_mc3479-0.4.4.dist-info/METADATA
micropython_mc3479-0.4.4.dist-info/WHEEL
micropython_mc3479-0.4.4.dist-info/top_level.txt
micropython_mc3479-0.4.4.dist-info/RECORD
