Metadata-Version: 2.1
Name: micropython-mc3479
Version: 0.4.4
Summary: MicroPython Driver for the MC3479 Accelerometer
Author-email: "Jose D. Montoya" <mc3479@mailmeto.mozmail.com>
License: MIT
Project-URL: Homepage, https://github.com/jposada202020/MicroPython_MC3479
Keywords: MicroPython,MC3479,accelerometer,sensor,acceleration
Classifier: Intended Audience :: Developers
Classifier: Topic :: Software Development :: Libraries
Classifier: Topic :: Software Development :: Embedded Systems
Classifier: Topic :: System :: Hardware
Classifier: License :: OSI Approved :: MIT License
Classifier: Programming Language :: Python :: Implementation :: MicroPython
License-File: LICENSE
